jaxamp/__about__.py
jaxamp/__init__.py
jaxamp/_amp.py
jaxamp/_dynamic_scaler.py
jaxamp-0.0.4.dist-info/METADATA
jaxamp-0.0.4.dist-info/WHEEL
jaxamp-0.0.4.dist-info/licenses/LICENSE.txt
jaxamp-0.0.4.dist-info/RECORD
