Metadata-Version: 2.1
Name: jaxamp
Version: 0.0.4
Summary: automatic mixed precision in JAX
Project-URL: Documentation, https://github.com/acutkosky/jaxamp#readme
Project-URL: Issues, https://github.com/acutkosky/jaxamp/issues
Project-URL: Source, https://github.com/acutkosky/jaxamp
Author-email: Ashok Cutkosky <ashok@cutkosky.com>
License-Expression: MIT
License-File: LICENSE.txt
Classifier: Development Status :: 4 - Beta
Classifier: Programming Language :: Python
Classifier: Programming Language :: Python :: 3.7
Classifier: Programming Language :: Python :: 3.8
Classifier: Programming Language :: Python :: 3.9
Classifier: Programming Language :: Python :: 3.10
Classifier: Programming Language :: Python :: 3.11
Classifier: Programming Language :: Python :: Implementation :: CPython
Classifier: Programming Language :: Python :: Implementation :: PyPy
Requires-Python: >=3.7
Requires-Dist: equinox>=0.11.0
Provides-Extra: dev
Requires-Dist: pytest>=7.4.0; extra == 'dev'
